[[{"location":"D:\\eclips_rpa\\eclipse\\plugins\\org.eclipse.jface_3.11.0.v20150602-1400.jar","type":"JAR","hints":{}},"org.eclipse.jface:org.eclipse.jface:3.11.0"],[{"location":"C:\\Program Files\\Java\\jre1.8.0_66","type":"JRE","hints":{"EXECUTION_ENVIRONMENT":"JavaSE-1.8"}},"jre:jre:1.8.0"],[{"location":"D:\\FPA_Git\\de.bht.fpa.mail.s000000.common\\libs\\java-mail-1.4.4.jar","type":"JAR","hints":{}},"com.sun.mail:javax.mail:1.4.4"],[{"location":"D:\\eclips_rpa\\eclipse\\plugins\\org.eclipse.swt.win32.win32.x86_64_3.104.1.v20150825-0743.jar","type":"JAR","hints":{}},"org.eclipse.swt:org.eclipse.swt.win32.win32.x86_64:3.104.0"]]